spiderforce4ai/__init__.py
spiderforce4ai/post_extraction_agent.py
spiderforce4ai-2.7.dist-info/METADATA
spiderforce4ai-2.7.dist-info/WHEEL
spiderforce4ai-2.7.dist-info/entry_points.txt
spiderforce4ai-2.7.dist-info/top_level.txt
spiderforce4ai-2.7.dist-info/RECORD
