Metadata-Version: 2.1
Name: spiderforce4ai
Version: 2.7
Summary: Python wrapper for SpiderForce4AI HTML-to-Markdown conversion service with LLM post-processing
Home-page: https://petertam.pro
Author: Piotr Tamulewicz
Author-email: Piotr Tamulewicz <pt@petertam.pro>
Project-URL: Homepage, https://petertam.pro
Project-URL: Documentation, https://petertam.pro/docs/spiderforce4ai
Project-URL: Repository, https://github.com/yourusername/spiderforce4ai
Project-URL: Bug Tracker, https://github.com/yourusername/spiderforce4ai/issues
Keywords: web-scraping,markdown,html-to-markdown,llm,ai,content-extraction,async,parallel-processing
Classifier: Development Status :: 4 - Beta
Classifier: Intended Audience :: Developers
Classifier: License :: OSI Approved :: MIT License
Classifier: Programming Language :: Python :: 3.11
Classifier: Programming Language :: Python :: 3.12
Classifier: Topic :: Internet :: WWW/HTTP :: Dynamic Content
Classifier: Topic :: Text Processing :: Markup :: Markdown
Classifier: Topic :: Software Development :: Libraries :: Python Modules
Classifier: Topic :: Scientific/Engineering :: Artificial Intelligence
Requires-Python: >=3.11
Requires-Dist: aiohttp>=3.8.0
Requires-Dist: asyncio>=3.4.3
Requires-Dist: rich>=10.0.0
Requires-Dist: aiofiles>=0.8.0
Requires-Dist: httpx>=0.24.0
Requires-Dist: litellm>=1.26.0
Requires-Dist: pydantic>=2.6.0
Requires-Dist: requests>=2.31.0
Requires-Dist: aiofiles>=23.2.1
Requires-Dist: et-xmlfile>=1.1.0
Requires-Dist: multidict>=6.0.4
Requires-Dist: openai>=1.12.0
Requires-Dist: pandas>=2.2.0
Requires-Dist: numpy>=1.26.0
Requires-Dist: yarl>=1.9.4
Requires-Dist: typing-extensions>=4.9.0
Provides-Extra: dev
Requires-Dist: pytest>=7.4.0; extra == "dev"
Requires-Dist: pytest-asyncio>=0.21.1; extra == "dev"
Requires-Dist: pytest-cov>=4.1.0; extra == "dev"
Requires-Dist: black>=23.7.0; extra == "dev"
Requires-Dist: isort>=5.12.0; extra == "dev"
Requires-Dist: mypy>=1.4.1; extra == "dev"
Requires-Dist: ruff>=0.1.8; extra == "dev"
Requires-Dist: pre-commit>=3.5.0; extra == "dev"
Provides-Extra: docs
Requires-Dist: sphinx>=7.1.0; extra == "docs"
Requires-Dist: sphinx-rtd-theme>=1.3.0; extra == "docs"
Requires-Dist: myst-parser>=2.0.0; extra == "docs"
Provides-Extra: test
Requires-Dist: pytest>=7.4.0; extra == "test"
Requires-Dist: pytest-asyncio>=0.21.1; extra == "test"
Requires-Dist: pytest-cov>=4.1.0; extra == "test"
Requires-Dist: pytest-mock>=3.12.0; extra == "test"
Requires-Dist: coverage>=7.4.0; extra == "test"
